multiresolutionfit/__init__.py
multiresolutionfit/countclass.py
multiresolutionfit/multiresolutionfit.py
multiresolutionfit-1.0.0.dist-info/METADATA
multiresolutionfit-1.0.0.dist-info/WHEEL
multiresolutionfit-1.0.0.dist-info/top_level.txt
multiresolutionfit-1.0.0.dist-info/RECORD
