Metadata-Version: 2.1
Name: multiresolutionfit
Version: 1.0.0
Summary: Multi Resolution Fit.
Home-page: https://github.com/duducosmos/multiresolutionfit
Author: Eduardo S. Pereira
Author-email: pereira.somoza@gmail.com
License: Apache License 2.0
Platform: UNKNOWN
Requires-Dist: numpy
Requires-Dist: numba
Requires-Dist: opencv-python
Requires-Dist: progressbar2
